nameuz/__init__.py
nameuz/cli.py
nameuz/core.py
nameuz-0.1.2.dist-info/METADATA
nameuz-0.1.2.dist-info/WHEEL
nameuz-0.1.2.dist-info/entry_points.txt
nameuz-0.1.2.dist-info/top_level.txt
nameuz-0.1.2.dist-info/RECORD
