Metadata-Version: 2.4
Name: nameuz
Version: 0.1.2
Summary: CLI tool and Python package for searching Uzbek name meanings from ismlar.com
Author-email: Abdulbosit Alijonov <info@alijonov.uz>
License: MIT
Project-URL: Homepage, https://github.com/AlijonovUz/nameuz
Project-URL: Source, https://github.com/AlijonovUz/nameuz
Requires-Python: >=3.8
Requires-Dist: requests
Requires-Dist: lxml
